patchwork/core/__init__.py
patchwork/core/component.py
patchwork/core/pydantic.py
patchwork/core/serializers.py
patchwork/core/typing.py
patchwork/core/utils.py
patchwork/core/client/__init__.py
patchwork/core/client/local.py
patchwork/core/client/publisher.py
patchwork/core/client/subscriber.py
patchwork/core/client/task.py
patchwork/core/client/serializers/__init__.py
patchwork/core/client/serializers/base.py
patchwork/core/client/serializers/betterproto.py
patchwork/core/config/__init__.py
patchwork/core/config/base.py
patchwork/core/proto/__init__.py
patchwork/core/proto/task.py
patchwork/core/proto/google/__init__.py
patchwork/core/proto/google/protobuf.py
patchwork/core/stubs/__init__.py
patchwork/core/stubs/prometheus.py
scripts/compile-protoc.py
tests/__init__.py
tests/conftest.py
tests/core/__init__.py
tests/core/test_classpath.py
tests/core/test_client.py
tests/core/test_component.py
tests/core/test_config.py
tests/core/test_fnpath.py
patchwork_core-0.2.10.dist-info/LICENSE
patchwork_core-0.2.10.dist-info/METADATA
patchwork_core-0.2.10.dist-info/WHEEL
patchwork_core-0.2.10.dist-info/top_level.txt
patchwork_core-0.2.10.dist-info/RECORD
