Metadata-Version: 2.1
Name: patchwork-core
Version: 0.2.10
Summary: Core of the Patchwork Framework - The distributed asynchronous microframework
Home-page: 
Author: Pawel Pecio
Author-email: 
Classifier: Development Status :: 5 - Production/Stable
Classifier: License :: OSI Approved :: MIT License
Classifier: Operating System :: POSIX :: Linux
Classifier: Programming Language :: Python :: 3.8
Classifier: Programming Language :: Python :: 3.9
Classifier: Programming Language :: Python :: 3.10
Classifier: Programming Language :: Python :: Implementation :: CPython
Classifier: Topic :: Software Development :: Libraries :: Application Frameworks
License-File: LICENSE
Requires-Dist: betterproto
Requires-Dist: google
Requires-Dist: pydantic ~=2.3
Requires-Dist: pytz
Requires-Dist: frozendict
